dgpsi/__init__.py
dgpsi/dgp.py
dgpsi/emulation.py
dgpsi/functions.py
dgpsi/gp.py
dgpsi/imputation.py
dgpsi/kernel_class.py
dgpsi/likelihood_class.py
dgpsi/linkgp.py
dgpsi/synthetic.py
dgpsi/utils.py
dgpsi/vecchia.py
dgpsi-2.6.0.dist-info/licenses/LICENSE
dgpsi-2.6.0.dist-info/METADATA
dgpsi-2.6.0.dist-info/WHEEL
dgpsi-2.6.0.dist-info/top_level.txt
dgpsi-2.6.0.dist-info/RECORD
