Metadata-Version: 2.4
Name: dgpsi
Version: 2.6.0
Summary: Deep and Linked Gaussian Process Emulations using Stochastic Imputation
Author-email: Deyu Ming <deyu.ming.16@ucl.ac.uk>
License: MIT
Project-URL: Homepage, https://github.com/mingdeyu/DGP
Keywords: surrogate modelling,deep learning,stochastic EM,elliptical slice sampling
Requires-Python: <3.13,>=3.9
License-File: LICENSE
Requires-Dist: numpy>=1.18.2
Requires-Dist: numba>=0.51.2
Requires-Dist: matplotlib>=3.2.1
Requires-Dist: tqdm>=4.50.2
Requires-Dist: scipy>=1.4.1
Requires-Dist: scikit-learn>=0.22.0
Requires-Dist: jupyter>=1.0.0
Requires-Dist: dill>=0.3.2
Requires-Dist: pathos>=0.2.9
Requires-Dist: multiprocess>=0.70.13
Requires-Dist: psutil>=5.8.0
Requires-Dist: tabulate>=0.8.7
Provides-Extra: interactive
Requires-Dist: jupyter; extra == "interactive"
Dynamic: license-file
